natansh_pattern/__init__.py
natansh_pattern/pattern.py
natansh_pattern-1.0.0.dist-info/METADATA
natansh_pattern-1.0.0.dist-info/WHEEL
natansh_pattern-1.0.0.dist-info/licenses/LICENCE.txt
natansh_pattern-1.0.0.dist-info/RECORD
